xml_json_yaml_convert/__init__.py
xml_json_yaml_convert/converter.py
xml_json_yaml_convert/version.py
xml_json_yaml_convert-1.0.3.dist-info/LICENSE
xml_json_yaml_convert-1.0.3.dist-info/METADATA
xml_json_yaml_convert-1.0.3.dist-info/WHEEL
xml_json_yaml_convert-1.0.3.dist-info/top_level.txt
xml_json_yaml_convert-1.0.3.dist-info/RECORD
